resolutiontree/core.py
resolutiontree/utils.py
resolutiontree-0.1.1.dist-info/METADATA
resolutiontree-0.1.1.dist-info/WHEEL
resolutiontree-0.1.1.dist-info/top_level.txt
resolutiontree-0.1.1.dist-info/RECORD
