Metadata-Version: 2.4
Name: resolutiontree
Version: 0.1.1
Summary: Systematic exploration of clustering resolutions in single-cell analysis
Author-email: Joe Hou <joseph.houjue@gmail.com>
License: MIT
Project-URL: Homepage, https://github.com/joe-jhou2/resolutiontree
Project-URL: Documentation, https://resolutiontree.readthedocs.io/
Project-URL: Repository, https://github.com/joe-jhou2/resolutiontree
Project-URL: Bug Tracker, https://github.com/joe-jhou2/resolutiontree/issues
Keywords: single-cell,clustering,resolution,scanpy,leiden,visualization
Classifier: Development Status :: 4 - Beta
Classifier: Intended Audience :: Science/Research
Classifier: Topic :: Scientific/Engineering :: Bio-Informatics
Classifier: License :: OSI Approved :: MIT License
Classifier: Programming Language :: Python :: 3
Classifier: Programming Language :: Python :: 3.8
Classifier: Programming Language :: Python :: 3.9
Classifier: Programming Language :: Python :: 3.10
Classifier: Programming Language :: Python :: 3.11
Requires-Python: >=3.8
